<library path="libhector_rviz_plugins">
  <class name="hector_rviz_plugins/GraphDisplay" type="hector_rviz_plugins::GraphDisplay" base_class_type="rviz::Display">
    <description>
      Displays a graph message.
    </description>
  </class>
  <class name="hector_rviz_plugins/HectorViewController" type="hector_rviz_plugins::HectorViewController" base_class_type="rviz::ViewController">
    <description>
      A view controller with support for animation, movement using the arrow keys, 2D and 3D mode as well as ROS interfaces for control by external nodes.
    </description>
  </class>
  <class name="hector_rviz_plugins/MultiRobotState" type="hector_rviz_plugins::MultiRobotStateDisplay" base_class_type="rviz::Display">
    <description>
      Displays multiple robot states.
    </description>
  </class>
  <class name="hector_rviz_plugins/PointCloudFilter" type="hector_rviz_plugins::PointCloudFilterDisplay" base_class_type="rviz::Display">
    <description>
      Displays a pointcloud but filters all points above a specified treshold around an axis.
    </description>
    <message_type>sensor_msgs/PointCloud2</message_type>
  </class>
</library>
